mtda/__init__.py
mtda/__version__.py
mtda/client.py
mtda/constants.py
mtda/discovery.py
mtda/main.py
mtda/pytest.py
mtda/utils.py
mtda/www.py
mtda/assets/addon-fit.js
mtda/assets/jquery.min.js
mtda/assets/keysight.js
mtda/assets/material_icons.css
mtda/assets/material_icons.ttf
mtda/assets/modern.min.css
mtda/assets/socket.io.min.js
mtda/assets/vnc.js
mtda/assets/winbox.bundle.min.js
mtda/assets/xterm.css
mtda/assets/xterm.js
mtda/assistant/__init__.py
mtda/assistant/assistant.py
mtda/assistant/homekit.py
mtda/console/__init__.py
mtda/console/docker.py
mtda/console/input.py
mtda/console/interface.py
mtda/console/logger.py
mtda/console/output.py
mtda/console/qemu.py
mtda/console/remote.py
mtda/console/screen.py
mtda/console/serial.py
mtda/console/telnet.py
mtda/console/usbf.py
mtda/keyboard/__init__.py
mtda/keyboard/controller.py
mtda/keyboard/hid.py
mtda/keyboard/qemu.py
mtda/power/__init__.py
mtda/power/aviosys_8800.py
mtda/power/controller.py
mtda/power/docker.py
mtda/power/gpio.py
mtda/power/pduclient.py
mtda/power/qemu.py
mtda/power/shellcmd.py
mtda/power/usbrelay.py
mtda/scripts/__init__.py
mtda/scripts/ipc227e.py
mtda/scripts/qemu.py
mtda/storage/__init__.py
mtda/storage/controller.py
mtda/storage/docker.py
mtda/storage/qemu.py
mtda/storage/samsung.py
mtda/storage/usbf.py
mtda/storage/usbsdmux.py
mtda/storage/writer.py
mtda/storage/helpers/__init__.py
mtda/storage/helpers/image.py
mtda/support/__init__.py
mtda/support/usb.py
mtda/templates/index.html
mtda/usb/__init__.py
mtda/usb/gpio.py
mtda/usb/qemu_mass_storage.py
mtda/usb/switch.py
mtda/video/__init__.py
mtda/video/controller.py
mtda/video/mjpg_streamer.py
mtda/video/qemu.py
mtda/video/ustreamer.py
mtda-0.32.data/scripts/mtda-cli
mtda-0.32.data/scripts/mtda-config
mtda-0.32.data/scripts/mtda-service
mtda-0.32.data/scripts/mtda-systemd-helper
mtda-0.32.data/scripts/mtda-ui
mtda-0.32.dist-info/COPYING
mtda-0.32.dist-info/METADATA
mtda-0.32.dist-info/WHEEL
mtda-0.32.dist-info/top_level.txt
mtda-0.32.dist-info/RECORD
